.DS_Store
pyedgeconnect/__init__.py
pyedgeconnect/ecos/__init__.py
pyedgeconnect/ecos/_alarm.py
pyedgeconnect/ecos/_bonded_tunnel.py
pyedgeconnect/ecos/_cli.py
pyedgeconnect/ecos/_cpu.py
pyedgeconnect/ecos/_deployment.py
pyedgeconnect/ecos/_disk_usage.py
pyedgeconnect/ecos/_dns.py
pyedgeconnect/ecos/_flows.py
pyedgeconnect/ecos/_gms.py
pyedgeconnect/ecos/_interfaces.py
pyedgeconnect/ecos/_license.py
pyedgeconnect/ecos/_local_subnets.py
pyedgeconnect/ecos/_login.py
pyedgeconnect/ecos/_memory.py
pyedgeconnect/ecos/_network_interfaces.py
pyedgeconnect/ecos/_nexthops.py
pyedgeconnect/ecos/_peers.py
pyedgeconnect/ecos/_ping_trace.py
pyedgeconnect/ecos/_port_forwarding.py
pyedgeconnect/ecos/_reboot.py
pyedgeconnect/ecos/_save_changes.py
pyedgeconnect/ecos/_security_maps.py
pyedgeconnect/ecos/_sp_portal.py
pyedgeconnect/ecos/_statistics.py
pyedgeconnect/ecos/_system_info.py
pyedgeconnect/ecos/_third_party_tunnel.py
pyedgeconnect/ecos/_time.py
pyedgeconnect/ecos/_traffic_class.py
pyedgeconnect/ecos/_tunnel.py
pyedgeconnect/ecos/_vrrp.py
pyedgeconnect/orch/__init__.py
pyedgeconnect/orch/_acls.py
pyedgeconnect/orch/_action_log.py
pyedgeconnect/orch/_active_sessions.py
pyedgeconnect/orch/_admin_distance.py
pyedgeconnect/orch/_advanced_properties.py
pyedgeconnect/orch/_aggregate_stats.py
pyedgeconnect/orch/_alarm.py
pyedgeconnect/orch/_api_key.py
pyedgeconnect/orch/_app_system_deploy_info.py
pyedgeconnect/orch/_app_system_state_info.py
pyedgeconnect/orch/_appliance.py
pyedgeconnect/orch/_appliance_backup.py
pyedgeconnect/orch/_appliance_crash_history.py
pyedgeconnect/orch/_appliance_extra_info.py
pyedgeconnect/orch/_appliance_preconfig.py
pyedgeconnect/orch/_appliance_reboot_history.py
pyedgeconnect/orch/_appliance_resync.py
pyedgeconnect/orch/_appliance_upgrade.py
pyedgeconnect/orch/_appliances_software_versions.py
pyedgeconnect/orch/_application_definition.py
pyedgeconnect/orch/_authentication.py
pyedgeconnect/orch/_avc_mode.py
pyedgeconnect/orch/_banners.py
pyedgeconnect-0.16.0a1.dist-info/LICENSE
pyedgeconnect-0.16.0a1.dist-info/METADATA
pyedgeconnect-0.16.0a1.dist-info/WHEEL
pyedgeconnect-0.16.0a1.dist-info/top_level.txt
pyedgeconnect-0.16.0a1.dist-info/RECORD
