Metadata-Version: 2.1
Name: pyedgeconnect
Version: 0.16.0a1
Summary: A Python wrapper for Aruba Orchestrator and Edge Connect API
Home-page: https://github.com/aruba/pyedgeconnect
Author: Zach Camara
Author-email: zachary.camara@hpe.com
License: MIT
Project-URL: Bug Reports, https://github.com/aruba/pyedgeconnect/issues
Project-URL: Source, https://github.com/aruba/pyedgeconnect/
Keywords: silverpeak,silverpeak python,aruba edgeconnect,edgeconnect
Classifier: Development Status :: 3 - Alpha
Classifier: Intended Audience :: Information Technology
Classifier: Intended Audience :: System Administrators
Classifier: Intended Audience :: Telecommunications Industry
Classifier: Topic :: System :: Networking
Classifier: License :: OSI Approved :: MIT License
Classifier: Programming Language :: Python :: 3
Classifier: Programming Language :: Python :: 3.7
Classifier: Programming Language :: Python :: 3.8
Classifier: Programming Language :: Python :: 3.9
Classifier: Programming Language :: Python :: 3.10
Classifier: Programming Language :: Python :: 3 :: Only
Classifier: Operating System :: OS Independent
Classifier: Natural Language :: English
Requires-Python: >=3.7, <4
License-File: LICENSE
Requires-Dist: requests
Provides-Extra: dev
Requires-Dist: black ; extra == 'dev'
Requires-Dist: flake8 ; extra == 'dev'
Requires-Dist: flake8-rst-docstrings ; extra == 'dev'
Requires-Dist: isort ; extra == 'dev'
Requires-Dist: sphinx ; extra == 'dev'
Requires-Dist: sphinx-rtd-theme ; extra == 'dev'
Requires-Dist: pytest ; extra == 'dev'
Requires-Dist: tox ; extra == 'dev'
